odoo/addons/photovoltaic_mgmt_extended/CHANGELOG.md
odoo/addons/photovoltaic_mgmt_extended/__init__.py
odoo/addons/photovoltaic_mgmt_extended/__manifest__.py
odoo/addons/photovoltaic_mgmt_extended/cliff.toml
odoo/addons/photovoltaic_mgmt_extended/i18n/es.po
odoo/addons/photovoltaic_mgmt_extended/i18n/photovoltaic_mgmt_extended.pot
odoo/addons/photovoltaic_mgmt_extended/models/__init__.py
odoo/addons/photovoltaic_mgmt_extended/models/account_allocation.py
odoo/addons/photovoltaic_mgmt_extended/models/contract_participation.py
odoo/addons/photovoltaic_mgmt_extended/models/participant_activities.py
odoo/addons/photovoltaic_mgmt_extended/models/participant_liquidations.py
odoo/addons/photovoltaic_mgmt_extended/models/photovoltaic_power_energy.py
odoo/addons/photovoltaic_mgmt_extended/models/photovoltaic_power_station.py
odoo/addons/photovoltaic_mgmt_extended/models/res_partner.py
odoo/addons/photovoltaic_mgmt_extended/models/res_partner_friend.py
odoo/addons/photovoltaic_mgmt_extended/models/res_partner_interest.py
odoo/addons/photovoltaic_mgmt_extended/scripts/filtro_email.py
odoo/addons/photovoltaic_mgmt_extended/scripts/generate_promotional_codes.py
odoo/addons/photovoltaic_mgmt_extended/security/ir.model.access.csv
odoo/addons/photovoltaic_mgmt_extended/views/account_allocation.xml
odoo/addons/photovoltaic_mgmt_extended/views/contract_participation.xml
odoo/addons/photovoltaic_mgmt_extended/views/photovoltaic_power_station.xml
odoo/addons/photovoltaic_mgmt_extended/views/res_partner.xml
odoo/addons/photovoltaic_mgmt_extended/views/res_partner_friend.xml
odoo/addons/photovoltaic_mgmt_extended/views/res_partner_interest.xml
odoo/addons/photovoltaic_mgmt_extended/wizard/__init__.py
odoo/addons/photovoltaic_mgmt_extended/wizard/account_allocation_state_update_wizard.py
odoo/addons/photovoltaic_mgmt_extended/wizard/account_allocation_state_update_wizard_view.xml
odoo_addon_photovoltaic_mgmt_extended-16.0.1.1.1.dist-info/METADATA
odoo_addon_photovoltaic_mgmt_extended-16.0.1.1.1.dist-info/WHEEL
odoo_addon_photovoltaic_mgmt_extended-16.0.1.1.1.dist-info/top_level.txt
odoo_addon_photovoltaic_mgmt_extended-16.0.1.1.1.dist-info/RECORD
