Metadata-Version: 2.1
Name: odoo-addon-photovoltaic_mgmt_extended
Version: 16.0.1.1.1
Requires-Python: >=3.10
Requires-Dist: odoo>=16.0a,<16.1dev
Summary: Photovoltaic Management Extended
License: LGPL-3
Author: Librecoop
Classifier: Programming Language :: Python
Classifier: Framework :: Odoo
Classifier: Framework :: Odoo :: 16.0
Classifier: License :: OSI Approved :: GNU Lesser General Public License v3 (LGPLv3)
